{"result":{"totCnt":7,"itemList":[{"cd":"091090","nm":"세원셀론텍","mt":"0","nv":2645,"cv":-30,"cr":-1.12,"rf":"5","pcv":2675,"mks":1637,"aq":168786,"aa":449,"ms":"OPEN"},{"cd":"006280","nm":"녹십자","mt":"0","nv":298000,"cv":-3500,"cr":-1.16,"rf":"5","pcv":301500,"mks":34826,"aq":162593,"aa":48400,"ms":"OPEN"},{"cd":"217730","nm":"강스템바이오텍","mt":"1","nv":8890,"cv":-240,"cr":-2.63,"rf":"5","pcv":9130,"mks":1865,"aq":326832,"aa":2919742,"ms":"OPEN"},{"cd":"078160","nm":"메디포스트","mt":"1","nv":27900,"cv":-1000,"cr":-3.46,"rf":"5","pcv":28900,"mks":4357,"aq":178906,"aa":5035587,"ms":"OPEN"},{"cd":"144510","nm":"녹십자랩셀","mt":"1","nv":55100,"cv":-2300,"cr":-4.01,"rf":"5","pcv":57400,"mks":5815,"aq":194618,"aa":10839791,"ms":"OPEN"},{"cd":"031390","nm":"녹십자셀","mt":"1","nv":50900,"cv":-2400,"cr":-4.5,"rf":"5","pcv":53300,"mks":6165,"aq":492051,"aa":24981130,"ms":"OPEN"},{"cd":"085660","nm":"차바이오텍","mt":"1","nv":21900,"cv":-1050,"cr":-4.58,"rf":"5","pcv":22950,"mks":11497,"aq":1371413,"aa":30283191,"ms":"OPEN"}],"itemInfoMap":{"144510":"녹십자그룹 계열의 바이오업체. NK면역세포치료제를 연구개발하는 것을 주요사업으로 영위하고 있으며, 제대혈은행사업도 영위. 18년4월 제대혈은행의 품질관리 능력 제고 및 표준가이드라인을 위해 유럽최고의 품질 인증기관인 독일의 TUV STU group으로부터 ISO9001:2015 인증 획득.","006280":"자회사 녹십자랩셀이 제대혈 보관사업(라이프라인)을 영위.","217730":"동종 제대혈유래 줄기세포치료제(의약품) 연구, 개발 업체. 자체 개발한 다분화능을 가진 줄기세포를 인간 제대혈로부터 고순도(high-purity)로 분리하고, 대량배양(massive culture)하는 기술을 기반으로 동종 제대혈유래 줄기세포치료제(의약품) 연구개발을 주요 사업으로 영위.","031390":"녹십자그룹 계열의 바이오업체로 제대혈 은행사업 등을 영위.","078160":"업계 상위의 제대혈 은행업체. 제대혈 줄기세포를 보관하였다가 치료에 필요시 공급하는 보관사업을 영위.","085660":"업계 상위의 제대혈 은행(아이코드)업체. 제대혈 줄기세포를 보관하였다가 치료에 필요시 공급하는 보관사업을 영위.","091090":"제대혈 은행(베이비셀)업체. 제대혈 줄기세포를 보관하였다가 치료에 필요시 공급하는 보관사업을 영위."}},"resultCode":"success"}