{"result":{"totCnt":49,"itemList":[{"cd":"357780","nm":"솔브레인","mt":"1","nv":250200,"cv":9200,"cr":3.82,"rf":"2","pcv":241000,"mks":19462,"aq":289891,"aa":69459938,"ms":"OPEN"},{"cd":"074600","nm":"원익QnC","mt":"1","nv":15150,"cv":500,"cr":3.41,"rf":"2","pcv":14650,"mks":3983,"aq":744064,"aa":11066739,"ms":"OPEN"},{"cd":"195870","nm":"해성디에스","mt":"0","nv":20650,"cv":400,"cr":1.98,"rf":"2","pcv":20250,"mks":3511,"aq":694865,"aa":14431,"ms":"OPEN"},{"cd":"101490","nm":"에스앤에스텍","mt":"1","nv":46350,"cv":850,"cr":1.87,"rf":"2","pcv":45500,"mks":9147,"aq":668629,"aa":30839926,"ms":"OPEN"},{"cd":"080580","nm":"오킨스전자","mt":"1","nv":8650,"cv":120,"cr":1.41,"rf":"2","pcv":8530,"mks":635,"aq":115059,"aa":984027,"ms":"OPEN"},{"cd":"059090","nm":"미코","mt":"1","nv":16350,"cv":200,"cr":1.24,"rf":"2","pcv":16150,"mks":5120,"aq":1327834,"aa":21259439,"ms":"OPEN"},{"cd":"031330","nm":"에스에이엠티","mt":"1","nv":2225,"cv":25,"cr":1.14,"rf":"2","pcv":2200,"mks":2225,"aq":960524,"aa":2141202,"ms":"OPEN"},{"cd":"083500","nm":"에프엔에스테크","mt":"1","nv":9090,"cv":40,"cr":0.44,"rf":"2","pcv":9050,"mks":762,"aq":79813,"aa":723996,"ms":"OPEN"},{"cd":"101160","nm":"월덱스","mt":"1","nv":12950,"cv":50,"cr":0.39,"rf":"2","pcv":12900,"mks":2138,"aq":617976,"aa":8141500,"ms":"OPEN"},{"cd":"057500","nm":"SKC 솔믹스","mt":"1","nv":6190,"cv":0,"cr":0.0,"rf":"3","pcv":6190,"mks":3806,"aq":0,"aa":0,"ms":"OPEN"},{"cd":"087730","nm":"에스모 머티리얼즈","mt":"1","nv":2720,"cv":0,"cr":0.0,"rf":"3","pcv":2720,"mks":266,"aq":0,"aa":0,"ms":"OPEN"},{"cd":"067310","nm":"하나마이크론","mt":"1","nv":7030,"cv":-20,"cr":-0.28,"rf":"5","pcv":7050,"mks":2135,"aq":1396027,"aa":9711360,"ms":"OPEN"},{"cd":"272110","nm":"케이엔제이","mt":"1","nv":12250,"cv":-50,"cr":-0.41,"rf":"5","pcv":12300,"mks":772,"aq":165606,"aa":2032941,"ms":"OPEN"},{"cd":"098120","nm":"마이크로컨텍솔","mt":"1","nv":4515,"cv":-25,"cr":-0.55,"rf":"5","pcv":4540,"mks":375,"aq":40798,"aa":181600,"ms":"OPEN"},{"cd":"008060","nm":"대덕","mt":"0","nv":6650,"cv":-40,"cr":-0.6,"rf":"5","pcv":6690,"mks":1901,"aq":231699,"aa":1537,"ms":"OPEN"},{"cd":"092220","nm":"KEC","mt":"0","nv":799,"cv":-6,"cr":-0.75,"rf":"5","pcv":805,"mks":932,"aq":363990,"aa":291,"ms":"OPEN"},{"cd":"060310","nm":"3S","mt":"1","nv":2360,"cv":-20,"cr":-0.84,"rf":"5","pcv":2380,"mks":1057,"aq":163545,"aa":387204,"ms":"OPEN"},{"cd":"092070","nm":"디엔에프","mt":"1","nv":15150,"cv":-150,"cr":-0.98,"rf":"5","pcv":15300,"mks":1630,"aq":190752,"aa":2882914,"ms":"OPEN"},{"cd":"095340","nm":"ISC","mt":"1","nv":20700,"cv":-250,"cr":-1.19,"rf":"5","pcv":20950,"mks":2927,"aq":242921,"aa":5076040,"ms":"OPEN"},{"cd":"219130","nm":"타이거일렉","mt":"1","nv":13700,"cv":-200,"cr":-1.44,"rf":"5","pcv":13900,"mks":865,"aq":43534,"aa":581268,"ms":"OPEN"}],"itemInfoMap":{"074600":"반도체 WAFER 생산시 소요되는 석영유리제품(Quartz Ware)과 반도체 및 LCD 생산시 사용되는 세라믹제품을 전문적으로 제조, 공급하는 업체.","092070":"반도체 소자 형성용 박막 재료 전문업체. 반도체 메모리 소자 및 디스플레이 산업의 핵심소재로 사용되는 유기금속화합물(ALD/CVD 전구체)을 개발, 제조, 판매 및 기술지원을 제공. 특히, Double Patterning Tech. 소재로 사용되는 DPT 제품과 캐패시터 유전막용 소재인 High-k 제품, LT(Low-temp)Sio/Sin용 소재인 HCDS 제품, 식각공정에 사용되는 하드마스크필름용 소재인 ACL 제품 등을 주요 제품으로 생산.","095340":"반도체 및 전자부품 검사장비의 소모성부품인 테스트소켓 제품(Test Socket, Inter-poser, Cycling Socket 등)을 생산하는 업체. Silicone Rubber를 기반으로 하는 반도체 IC 테스트 소켓을 국내 최초로 개발, 세계 최초로 양산화에 성공. 주요 매출처로 삼성전자, SK하이닉스 등.","241770":"반도체 장비용 부품 및 반도체 공정재료 생산업체. 반도체 제조공정의 원재료인 전구체와 반도체 장비의 챔버내에서 웨이퍼를 흡착하고 가열해주는 히터블럭을 주력으로 생산.","036490":"반도체, 디스플레이, 태양전지 제조 과정에 사용되는 특수가스(NF3, SiH4, WF6 등) 제조/생산 전문업체.","057500":"SK그룹 계열의 반도체 및 FPD 부품소재 전문기업. Al2O3(알루미나), Si(실리콘), SiC(실리콘 카바이드) 소재를 기반으로 반도체 및 FPD 부품소재의 생산과 가공을 통하여 제품을 판매하는 사업을 영위중. 주요 매출처는 삼성전자, SK하이닉스, LG디스플레이 등이 있음.","060310":"반도체 웨이퍼캐리어박스(FOSB)와 냉난방환경시험설비 시공/설치/판매 업체.","272110":"디스플레이 패널 관련 Edge Grinder(엣지그라인더)와 CVD-SiC(탄화규소) Product 생산 업체.  CVD-SiC(탄화규소) 제품분야에서 반도체 웨이퍼 에칭공정용 소모품 SiC Ring 등을 생산. 주 수요처는 SK하이닉스.","077360":"반도체 패키징 재료인 솔더볼(Solder Ball) 제조/판매 사업을 영위.","008060":"반도체 패키지 공정에 사용되는 PKG(Package Substrate)를 제작 및 판매하는 업체.","281820":"디스플레이 및 반도체 공정에 사용되는 전공정 장비 및 소모성 재료 생산, 판매.","170920":"디스플레이나 반도체 제조 공정에 사용되는 공정소재(Process Chemical) 중 하나인 박리액 개발 및 제조를 주력사업으로 영위. 주력 매출처는 삼성디스플레이 등.","281740":"유기금속화학물 설계 및 TMA(Trimethyl Aluminium) 제조기술을 기반으로 하여 LED, 메탈로센촉매, 디스플레이, Solar, 반도체 등의 소재로 사용되는 초고순도 유기금속 화합물을 개발 및 공급 중. 국내 유일 TMA 제조 기술을 확보하고 있으며, 전세계 TMA를 제조하는 업체 중 LED, 반도체, Solar, 촉매 사업을 전부 영위할수 있는 회사는 당사가 유일.","102710":"반도체 및 디스플레이용 전자재료 전문 제조업체. 반도체 소재인 프로세스케미칼(신너, 현상액, 식각액, 박리액 등), 반도체 포토레지스트용 핵심원료인 화인케미칼 등을 제조하여 국내외 반도체 제조업체에 판매중.","059090":"반도체/디스플레이용 장비를 구성하는 부품 제작 업체. 주요 제품으로는 Heater, ESC  및 세라믹 부품 등이 있음.","171010":"전자재료 화학 소재 전문업체. 주로 반도체나 디스플레이 산업 공정 중에 쓰이는 식각액과 박리액, 세정액, 증착액, 용해액 등을 제조, 판매.","101160":"반도체 에칭공정에 사용되는 반도체용 장비재료인 실리콘(실리콘링 및 실리콘전극 등), 쿼츠, 알루미나 등을 생산하는 업체. 주요 매출처로 삼성전자, SK하이닉스 등.","092220":"반도체제품 및 부품 제조 전문업체. 전력제어/전류증폭용 트랜지스터(TR), 집적회로(IC) 등을 생산, 판매. 주력제품은 소신호트랜지스터(SSTR)로 낮은 전력소비를 필요로 하는 모바일 기기에 사용되는 전자제품.","089030":"반도체 소모품(C.O.K 등) 제조 및 판매 업체.","098120":"반도체 및 전자부품의 검사에 필수적으로 사용되는 부품인 IC Socket 전문 제조업체. 단품상태의 메모리반도체의 번인테스트(Burn-In Test)를 위한 번인소켓 및 모듈상태의 메모리테스트를 위한 모듈소켓, SSD Test용 Interface 등을 생산/판매.","147760":"반도체 검사용 프로브 카드 전문업체. 반도체 제조공정 중 반도체 소자의 전기적 기능의 검사를 위한 테스트 공정에 소요되는 프로브 카드(Probe Card) 제조 및 판매를 주요 사업으로 영위.","219130":"인쇄회로기판(PCB) 전문 제조업체. 반도체 후공정의 검사공정에 사용되는 고다층(High-Multilayer), 고밀도(Fine Pitch)의 PCB를 주로 생산. 주요 제품으로는 반도체 작동 유무를 검사하는 핵심 부품인 Probe Card PCB, 반도체 device의 전기적 특성 평가용 Load Board PCB, 반도체 패키지 테스트용 Socket Board PCB, 반도체의 고온에 대한 내구성 테스트용 Burn in Board PCB 등이 있음.","114810":"반도체 및 디스플레이(LCD, OLED) 관련 초정밀 가공/세정 업체.","144960":"반도체 및 디스플레이(Solar 포함) 박막공정 및 식각공정 장비에 사용되는 핵심 부품 공급 업체. 주요 제품으로는 박막공정 진행 후 공정내 잔존하는 부산물에 대한 Plasma Cleaning를 실시하는 핵심 모듈인 Remote Plasma Generator(RPG), 박막 공정이나 건식각 공정장비의 진공 방(Vacuum Chamber)에 가스를 공급하여 Plasma를 발생하는데 필요한 전원을 공급하는 모듈인 RF Generator(RFG) 및 Matcher(MAT) 등이 있음.","357780":"반도체 및 디스플레이 공정용 화학재료, 2차전지 소재 등 생산/판매 업체. 삼성전자, SK하이닉스, LG디스플레이 등 국내 반도체 및 디스플레이 제조사에 공정용 화학 재료 등을 공급.","036810":"반도체 재료/장비 전문업체. 포토마스크용 보호막인 펠리클(Pellicle)과 반도체공정중 온도조절장비인 칠러(Chiller)를 주력으로 생산.","241790":"반도체 공정용 화학재료와 반도체FAB(전공정 생산라인) 설비 등에 적용되는 장비 생산 업체. 화학재료 부문은 HCDS, TiCl4 등 전구체(Precursor)등 특수가스를 비롯한 수종의 반도체 제조 공정용 화학제품을 생산하여 공급. 반도체장비 부문에서는 화학물질 중앙공급장치(반도체 케미칼 공급장치)를 제조 설치하고 유지보수하는 사업을 영위.","094170":"휴대폰, 태블릿, 기타 전자기기에 들어가는 아날로그(Analog) 반도체를 회로설계, 개발 및 일괄 외주생산 상용화하여 고객사에 판매하는 팹리스(Fabless) 아날로그 반도체 업체. 주력 제품은 모바일 카메라용 AF Driver IC이며, 모바일LCD/AMOLED 전원 IC, LED 조명 Driver IC 등도 생산.","195870":"해성그룹 계열의 리드프레임 및 반도체 패키지용 Substrate 제작, 판매를 주요 사업으로 영위하는 업체. 주요 제품으로는 FBGA 및 Fc-FBGA(2Layer), ELF(Etched IC Leadframe), SLF(Stamped IC Leadframes) 등.","101490":"블랭크 마스크 제조업체. 블랭크마스크는 반도체 및 LCD, OLED 노광 공정의 핵심재료인 포토마스크의 원재료임.","127160":"반도체 및 LED 리드프레임과 LED package 제조, SMT(표면실장기술) 사업을 영위.","317330":"OLED의 핵심구성요소인 유기재료와 반도체 전자재료 등의 화학제품을 전문적으로 생산하는 업체. 반도체용 증착소재(Precursor) 및 합성수지용 고분자 촉매 등 전자재료 소재의 유,무기 합성을 전문으로 하는 반도체사업 영위.","278280":"디스플레이소재(LCD 식각액첨가제, OLED소재), 반도체 공정소재(SOH공정첨가제), 2차전지소재(전해질, 전해액 첨가제), 의약품 중간체(결핵치료제, 당뇨병치료제 등) 및 정밀화학 사업(질산 칼륨, 질산리튬 등) 등을 영위하는 업체. 반도체공정소재는 반도체 제조공정에서 초미세 선폭의 패턴을 구현하는데 정확성을 제고하는 역할을 담당(수율 및 품질개선, 생산성 향상, 설비투자 절감 효과)하는 소재로서 국내 시장 점유율 90% 이상을 차지.","031330":"메모리를 포함한 각종 반도체 및 LCD 패널 등을 판매하고 있는 IT부품 유통업체. 삼성전자, 삼성디스플레이, 삼성전기, 삼성SDI 등의 IT기업들과 안정적인 공급계약을 체결하고, 스마트폰 및 디지탈카메라, TabletPC와 같은 IT 제품에 필요한 Memory, LCD패널, 시스템반도체, Digital Module 제품 등을 판매중.","080580":"반도체 검사용 소켓 제조업체. 반도체 후공정 과정에서 칩의 불량 여부를 검사하는 부품인 \"번인소켓(Burn-In Socket)\"을 주로 생산. 삼성전자, SK하이닉스 등이 주요 고객.","005290":"감광액과 발포제 생산/판매업체. 반도체 및 평판디스플레이 등의 노광공정에 사용되는 감광액(Photo Resist) 관련 전자재료사업을 영위.","087730":"반도체 칩 외부를 밀봉하는 재료인 EMC(에폭시 몰딩 컴파운드)와 LED(발광다이오드)칩을 보호하는 소재 CMC(클리어 몰딩 컴파운드)를 생산하는 업체.","033160":"반도체 Package의 핵심부품인 본딩와이어(Bonding Wire) 및 솔더볼(Solder Ball) 등을 생산하는 업체. 주요 제품은 Gold Bonding Wire(99.99%), 고순도 Gold Sputtering Target(99.999%), Gold합금 Sputtering Target, 고순도 Gold Evaporate Material(99.999%), BGA Solder Ball 등.","166090":"반도체 용 실리콘부품 소재 및 부품 생산업체. 반도체 생산시 사용되는 Silicon Ring 및 Silicon Electrode의 생산 및 판매를 주요 사업 영위.","104830":"2006년 12월 구 원익IPS의 특수가스사업부문이 물적분할한 업체. 반도체 및 디스플레이 생산공정에 사용되는 특수가스 생산을 주요 사업으로 영위. 삼성전자, SK하이닉스 등의 종합반도체회사를 주요 고객사로 두고 있으며, 반도체 이외에도 삼성디스플레이 AMOLED 사업부에 공정용 특수가스를 공급중.","024850":"반도체 구조재료인 리드프레임(반도체 패키지의 내부와 외부를 연결해 주는 전기도선의 역할과 반도체를 지지해 주는 버팀대의 역할) 생산업체.","093370":"불소를 기반으로 한 가전 및 냉매가스와 반도체용 특수가스, 2차전지 재료 및 자동차용 냉매가스 생산업체. 리튬2차전지용 전해질 소재인 LiPF6 및 반도체용 특수가스 C4F6 등을 제조, 판매.","052900":"반도체 재료 및 SSD 사업을 주요사업으로 영위하는 업체. 주요 제품으로는 반도체재료인 IC-Tray, Module-Tray, SSD CASE 등임.","272290":"연성회로기판(FPCB)용 소재(주요상표-INNOFLEX, SMARTFLEX) 및 반도체 패키지용 소재(주요상표-INNOSEM) 등을 개발, 제조, 판매하는 부품 소재업체.","033640":"반도체사업(디스플레이용 Driver IC의 Bumping, WLP 및 Package 등), 전자재료사업(반도체, LCD 등의 제조공정용 Chemical) 등을 영위하는 업체.","036830":"반도체 및 디스플레이 공정용 화학재료, 2차전지 소재 등 생산/판매 업체. 삼성전자, SK하이닉스, LG디스플레이 등 국내 반도체 및 디스플레이 제조사에 공정용 화학 재료 등을 공급중이며, 삼성SDI, SK이노베이션, LG화학 등 국내 2차전지 제조사에 관련 제품을 공급중.","064760":"반도체, 태양전지 및 LED용 부품 전문 제조업체. 고순도 흑연(Graphite)을 이용한 반도체 및 태양전지용 실리콘 잉곳을 생산하는 Growing 장비용 Graphite 부품(이하 고순도 흑연 제품)을 제조, 판매. 반도체 Device업체에서 사용하는 장비의 Solid SiC Wafer, Ring 및 SiC제품 등도 판매중.","067310":"반도체 재료(반도체식각장비의 Silicon parts 등) 업체 하나머티리얼즈(주)를 종속회사로 보유.","083500":"반도체 및 디스플레이(OLED) 공정용 장비, 부품, 소재업체. 주요 제품으로 디스플레이 제조장비와 부품소재인 UV LAMP, CMP PAD, OLED MASK 세정 등이 있음."}},"resultCode":"success"}