{"result":{"totCnt":13,"itemList":[{"cd":"131290","nm":"티에스이","mt":"1","nv":43850,"cv":3850,"cr":9.63,"rf":"2","pcv":40000,"mks":4850,"aq":144677,"aa":6101581,"ms":"OPEN"},{"cd":"053610","nm":"프로텍","mt":"1","nv":26500,"cv":0,"cr":0.0,"rf":"3","pcv":26500,"mks":2915,"aq":210354,"aa":5538042,"ms":"OPEN"},{"cd":"049080","nm":"기가레인","mt":"1","nv":1040,"cv":-20,"cr":-1.89,"rf":"5","pcv":1060,"mks":544,"aq":182055,"aa":189780,"ms":"OPEN"},{"cd":"049950","nm":"미래컴퍼니","mt":"1","nv":27550,"cv":-650,"cr":-2.3,"rf":"5","pcv":28200,"mks":2304,"aq":36171,"aa":1004026,"ms":"OPEN"},{"cd":"064760","nm":"티씨케이","mt":"1","nv":89100,"cv":-2100,"cr":-2.3,"rf":"5","pcv":91200,"mks":10402,"aq":45764,"aa":4103302,"ms":"OPEN"},{"cd":"080530","nm":"코디","mt":"1","nv":1895,"cv":-45,"cr":-2.32,"rf":"5","pcv":1940,"mks":453,"aq":363338,"aa":711222,"ms":"OPEN"},{"cd":"042700","nm":"한미반도체","mt":"0","nv":11850,"cv":-350,"cr":-2.87,"rf":"5","pcv":12200,"mks":6103,"aq":4841376,"aa":61505,"ms":"OPEN"},{"cd":"138690","nm":"엘아이에스","mt":"1","nv":8710,"cv":-290,"cr":-3.22,"rf":"5","pcv":9000,"mks":1396,"aq":58993,"aa":518495,"ms":"OPEN"},{"cd":"306620","nm":"네온테크","mt":"1","nv":2605,"cv":-95,"cr":-3.52,"rf":"5","pcv":2700,"mks":966,"aq":292767,"aa":768717,"ms":"OPEN"},{"cd":"036930","nm":"주성엔지니어링","mt":"1","nv":7570,"cv":-280,"cr":-3.57,"rf":"5","pcv":7850,"mks":3652,"aq":853105,"aa":6494800,"ms":"OPEN"},{"cd":"122640","nm":"예스티","mt":"1","nv":8590,"cv":-320,"cr":-3.59,"rf":"5","pcv":8910,"mks":1239,"aq":103918,"aa":897320,"ms":"OPEN"},{"cd":"039030","nm":"이오테크닉스","mt":"1","nv":117500,"cv":-5000,"cr":-4.08,"rf":"5","pcv":122500,"mks":14475,"aq":122451,"aa":14442191,"ms":"OPEN"},{"cd":"065130","nm":"탑엔지니어링","mt":"1","nv":11350,"cv":-550,"cr":-4.62,"rf":"5","pcv":11900,"mks":1813,"aq":1080707,"aa":12428622,"ms":"OPEN"}],"itemInfoMap":{"065130":"반도체, LCD, LED Chip 제조 및 OLED 공정장비 제조를 주력사업으로 영위. LED Chip 제조 장비중 핵심장비인 MO-CVD 장비를 바탕으로 Fab 공정상의 PE-CVD, Etcher 장비, 그리고 패키지 공정상의 주요 장비 개발에 성공하여 LED Chip제조장비를 일괄 공급.","039030":"반도체 레이저마커, 레이저응용기기 제조 및 판매를 주요 사업으로 영위. 레이저를 이용하여 반도체, PCB, Display(LCD, OLED 등), 휴대폰 산업의 주요 생산 장비를 제조하여 국내외로 공급중. 반도체 생산 장비인 Laser Marker, Laser Cutter 등이 주요제품.","053610":"반도체장비, 표면실장공정(SMT) 및 LED 장비 제조업체. LED DIE BONDER 등을 생산.","138690":"레이저를 이용하여 다양한 산업분야에 적용하는 레이저 응용기기 전문업체. LED TV의 핵심부품인 도광판을 레이저로 패터닝 할 수 있는 장비(Laser LGP Engraving M/C)를 생산.","049080":"RF통신부품 및 반도체장비 제조업체로 LED 장비 중 전공정 식각 장비에 해당하는 LED Etcher 장비를 생산.","036930":"LED장비인 GaN MO CVD(유기금속 화학증착 장비) 생산. GaN MO CVD는 녹색, 청색, 백색 등의 단파장 LED의 대량 생산을 위한 장비임.","122640":"디스플레이(LCD, LED, OLED) 및 반도체 장비 제조/판매 업체. 주요 제품으로 삼성전자 반도체 생산공정과 삼성디스플레이의 FPD 패널 생산공정에 투입되는 열처리, 온도제어 및 검사장비 등이 있음. 주요고객사는 삼성전자, 삼성디스플레이.","042700":"다이본딩, 몰딩, 레이저마킹 등의 LED제조용 장비 생산.","131290":"반도체 및 디스플레이(OLED/LED) 검사장비 제조/판매 업체. 주요제품으로 Interface Board(메모리 반도체 검사장비), Probe Card(반도체 웨이퍼 검사장비), Total Test Solution, OLED Tester 등이 있음.","064760":"LED 소자제조 공정 장비용 부분품 생산. LED 증착(MOCVD) 공정에서 LED 웨이퍼를 지지하는 서스셉터(Susceptor)를 국산화에 성공하여 국내외 발광 소자 및 장비 업체에 납품.","080530":"경기도 용인시에 위치한 본사에서 LED 검사장치 생산.","049950":"OLED, LED장비 등의 제품 생산공정에 필요한 Edge Grinder(LCD 패널의 단면을 다듬는 장비), Edge Inspection(LCD 패널 검사장비) 등을 주력 제품으로 생산.","306620":"자동화 설비(FA System) 중 제어장치 및 모터 상품 제조, 반도체/LED/MLCC용 절단 장비 제조 등을 주력 사업으로 영위. 반도체/LED/MLCC용 절단 장비 부문 주요 제품으로는 Dicing Saw(반도체/LED), Saw & Sorter(반도체/PCB), MLCC Cutter(MLCC), Micro LED Cutting(PCB Panel) 등이 있음."}},"resultCode":"success"}