{"result":{"totCnt":11,"itemList":[{"cd":"034120","nm":"SBS","mt":"0","nv":16200,"cv":100,"cr":0.62,"rf":"2","pcv":16100,"mks":2957,"aq":82899,"aa":1329,"ms":"OPEN"},{"cd":"000080","nm":"하이트진로","mt":"0","nv":44700,"cv":-100,"cr":-0.22,"rf":"5","pcv":44800,"mks":31350,"aq":472912,"aa":21310,"ms":"OPEN"},{"cd":"088910","nm":"동우팜투테이블","mt":"1","nv":3375,"cv":-15,"cr":-0.44,"rf":"5","pcv":3390,"mks":872,"aq":127869,"aa":433281,"ms":"OPEN"},{"cd":"136480","nm":"하림","mt":"1","nv":2785,"cv":-25,"cr":-0.89,"rf":"5","pcv":2810,"mks":2958,"aq":552421,"aa":1539675,"ms":"OPEN"},{"cd":"000140","nm":"하이트진로홀딩스","mt":"0","nv":21600,"cv":-200,"cr":-0.92,"rf":"5","pcv":21800,"mks":5013,"aq":17150,"aa":375,"ms":"OPEN"},{"cd":"046140","nm":"SBS콘텐츠허브","mt":"1","nv":6090,"cv":-70,"cr":-1.14,"rf":"5","pcv":6160,"mks":1307,"aq":39237,"aa":237075,"ms":"OPEN"},{"cd":"027740","nm":"마니커","mt":"0","nv":762,"cv":-12,"cr":-1.55,"rf":"5","pcv":774,"mks":1208,"aq":2188304,"aa":1669,"ms":"OPEN"},{"cd":"067160","nm":"아프리카TV","mt":"1","nv":60200,"cv":-1400,"cr":-2.27,"rf":"5","pcv":61600,"mks":6920,"aq":129170,"aa":7821206,"ms":"OPEN"},{"cd":"027710","nm":"팜스토리","mt":"1","nv":1210,"cv":-30,"cr":-2.42,"rf":"5","pcv":1240,"mks":1348,"aq":757729,"aa":918817,"ms":"OPEN"},{"cd":"044480","nm":"경남바이오파마","mt":"1","nv":4945,"cv":-145,"cr":-2.85,"rf":"5","pcv":5090,"mks":705,"aq":189654,"aa":937653,"ms":"OPEN"},{"cd":"035810","nm":"이지홀딩스","mt":"1","nv":4855,"cv":-145,"cr":-2.9,"rf":"5","pcv":5000,"mks":2701,"aq":926964,"aa":4528293,"ms":"OPEN"}],"itemInfoMap":{"088910":"닭고기 원료육 전문업체. 농림수산식품부지정 가축(육계)계열화 업체로서 양계, 종란, 부화, 사육, 가공, 판매에 이르는 전과정을 일괄적으로 영위.","034120":"태영그룹 계열의 국내 최대 규모 민영방송사. 2024년까지 올림픽 중계권을 확보.","067160":"Afreeca TV를 중심으로 인터넷 기반 서비스를 제공하는 업체. 소셜미디어 플랫폼 “AfreecaTV”를 중심으로 국내 개인방송 시장에서 독보적 입지를 확보.","044480":"콘돔 생산업체(월드컵 기간에 판매량 급증).","027710":"삼계탕, 삼계죽 등을 생산하는 육가공 전문업체 마니커에프앤지의 최대주주.","046140":"SBS방송프로그램 등의 콘텐츠 유통사업 영위. IPTV, DMB TV, 모바일, 인터넷, 케이블TV, 해외배급 등 국내외 다양한 미디어에 콘텐츠 유통 사업을 진행하고 있음. 그룹 계열사인 SBS가 2024년까지 올림픽 중계권을 확보.","035810":"닭고기업체 마니커의 최대주주(월드컵, 올림픽시즌 수요 증가 기대감).","000080":"국내 대표적인 주류업체. 소주(참이슬, 참이슬fresh, 과일소주 등), 맥주(테라, 하이트, 맥스, 드라이d, 필라이트 등), 복분자 와인, 이슬톡톡, 망고링고 등을 생산. 스포츠행사시 매출증가 기대감 작용.","136480":"하림 닭고기, 하림 치킨너겟, 하림 사료 등의 브랜드를 가진 국내 닭고기 시장 선두업체.","027740":"닭고기 전문업체로 종계, 부화, 사육, 도계, 육가공, 유통에 이르는 수직계열화 구축. 스포츠행사 기간중 닭고기 소비 증가로 부각.","000140":"하이트진로그룹 계열의 지주회사. 상장사인 하이트진로(주)를 비롯해 하이트진로산업(주), (주)진로소주 등 맥주와 소주, 위스키 및 주정 등을 취급하는 주류전문 회사들을 자회사, 손자회사로 보유."}},"resultCode":"success"}