{"result":{"totCnt":25,"itemList":[{"cd":"080160","nm":"모두투어","mt":"1","nv":12600,"cv":1300,"cr":11.5,"rf":"2","pcv":11300,"mks":2381,"aq":5314937,"aa":69979281,"ms":"OPEN"},{"cd":"001130","nm":"대한제분","mt":"0","nv":182500,"cv":13000,"cr":7.67,"rf":"2","pcv":169500,"mks":3084,"aq":65656,"aa":11663,"ms":"OPEN"},{"cd":"039130","nm":"하나투어","mt":"0","nv":41900,"cv":2850,"cr":7.3,"rf":"2","pcv":39050,"mks":5841,"aq":2085379,"aa":91058,"ms":"OPEN"},{"cd":"003490","nm":"대한항공","mt":"0","nv":19750,"cv":850,"cr":4.5,"rf":"2","pcv":18900,"mks":34406,"aq":7718573,"aa":151853,"ms":"OPEN"},{"cd":"004020","nm":"현대제철","mt":"0","nv":28250,"cv":700,"cr":2.54,"rf":"2","pcv":27550,"mks":37698,"aq":1598970,"aa":44776,"ms":"OPEN"},{"cd":"004370","nm":"농심","mt":"0","nv":383000,"cv":9000,"cr":2.41,"rf":"2","pcv":374000,"mks":23297,"aq":55026,"aa":21031,"ms":"OPEN"},{"cd":"271560","nm":"오리온","mt":"0","nv":148500,"cv":3500,"cr":2.41,"rf":"2","pcv":145000,"mks":58711,"aq":50358,"aa":7376,"ms":"OPEN"},{"cd":"007310","nm":"오뚜기","mt":"0","nv":603000,"cv":13000,"cr":2.2,"rf":"2","pcv":590000,"mks":21740,"aq":18585,"aa":11285,"ms":"OPEN"},{"cd":"036460","nm":"한국가스공사","mt":"0","nv":26200,"cv":500,"cr":1.95,"rf":"2","pcv":25700,"mks":24186,"aq":306175,"aa":7881,"ms":"OPEN"},{"cd":"001680","nm":"대상","mt":"0","nv":26900,"cv":400,"cr":1.51,"rf":"2","pcv":26500,"mks":9320,"aq":450207,"aa":12213,"ms":"OPEN"},{"cd":"049770","nm":"동원F&B","mt":"0","nv":186000,"cv":1000,"cr":0.54,"rf":"2","pcv":185000,"mks":7178,"aq":6554,"aa":1213,"ms":"OPEN"},{"cd":"001230","nm":"동국제강","mt":"0","nv":6410,"cv":30,"cr":0.47,"rf":"2","pcv":6380,"mks":6117,"aq":659208,"aa":4177,"ms":"OPEN"},{"cd":"020560","nm":"아시아나항공","mt":"0","nv":4480,"cv":15,"cr":0.34,"rf":"2","pcv":4465,"mks":10001,"aq":7573978,"aa":34133,"ms":"OPEN"},{"cd":"005490","nm":"POSCO","mt":"0","nv":207000,"cv":0,"cr":0.0,"rf":"3","pcv":207000,"mks":180477,"aq":269241,"aa":55542,"ms":"OPEN"},{"cd":"000080","nm":"하이트진로","mt":"0","nv":44700,"cv":-100,"cr":-0.22,"rf":"5","pcv":44800,"mks":31350,"aq":472912,"aa":21310,"ms":"OPEN"},{"cd":"010950","nm":"S-Oil","mt":"0","nv":63600,"cv":-400,"cr":-0.62,"rf":"5","pcv":64000,"mks":71603,"aq":373538,"aa":23842,"ms":"OPEN"},{"cd":"002680","nm":"한탑","mt":"1","nv":1805,"cv":-15,"cr":-0.82,"rf":"5","pcv":1820,"mks":403,"aq":56709,"aa":101833,"ms":"OPEN"},{"cd":"005880","nm":"대한해운","mt":"0","nv":16450,"cv":-150,"cr":-0.9,"rf":"5","pcv":16600,"mks":4018,"aq":51145,"aa":843,"ms":"OPEN"},{"cd":"000070","nm":"삼양홀딩스","mt":"0","nv":72300,"cv":-700,"cr":-0.96,"rf":"5","pcv":73000,"mks":6192,"aq":22606,"aa":1637,"ms":"OPEN"},{"cd":"001790","nm":"대한제당","mt":"0","nv":19700,"cv":-250,"cr":-1.25,"rf":"5","pcv":19950,"mks":1767,"aq":16406,"aa":323,"ms":"OPEN"}],"itemInfoMap":{"271560":"비스킷, 초콜릿, 껌, 파이 등의 각종 과자류를 생산, 판매하는 업체. 원재료(유지류, 분유류 등) 수입 비중이 높아 환율하락시 수혜주로 부각됨.","005490":"국내 철강시장에서의 독점적 지위와 세계적인 경쟁력을 보유하고 있는 종합제철업체. 원재료(철강석, 석탄, STS원료 등) 수입비중이 높아 환율하락시 수혜주로 부각.","010950":"국내 대표적인 정유사. 세계적 수준의 중질유 분해 시설을 갖추고 있는 석유정제 및 판매업체. 환율하락시 원유 비용절감 효과로 수혜주로 부각.","080160":"여행주는 환율하락시 내국인의 해외여행 비용 부담이 줄어 여행객 수가 증가하는 특성이 있기 때문에 대표적인 환율하락 수혜주로 분류.","002680":"동사가 영위하는 제분업 및 사료제조업은 업종 특성상 환율 및 원재료의 국제 가격 동향에 민감함.","003010":"건설기계 및 육상용 발전기, 선박 및 산업용 엔진/발전기 수입판매 전문업체. 세계 최대의 중장비 제조업체인 美 캐터필러를 비롯해 Metso, Jungheinrich, Vermeer 社의 한국내 독점 딜러 및 대리점으로서 캐터필러 제품의 매출 비중이 높음. 수입판매 비중이 높아 환율하락시 수혜주로 부각됨.","001130":"제분업 및 소맥분 판매업 등을 주요사업으로 영위하고 있는 업체. 원재료(원맥 등) 수입 비중이 높아 환율하락시 수혜주로 부각.","001790":"제당사업(설탕 등) 및 사료사업(가축용 배합사료)을 영위하는 음식료품 제조업체. 원재료(원당, 옥수수, 코코아 등) 수입 비중이 높아 환율하락시 수혜주로 부각.","001230":"판재류(후판)과 봉형강류(철근, 형강) 등을 생산하는 철강제조 전문업체. 원재료(수입고철, 선철, SLAB 등) 수입 비중이 높아 환율하락시 수혜주로 부각.","049770":"동원산업㈜으로부터 분할 설립된 동원그룹 계열의 종합식품회사.  참치캔, 캔햄, 냉동만두, 어묵, 맛살, 죽, 발효유, 치즈 등의 식품사업 영위. 원재료(원어, 돈육 등) 수입 비중이 높아 환율하락시 수혜주로 부각.","000080":"원재료(맥아, 포장재료 등) 수입 비중이 높아 환율하락시 수혜주로 부각.","003490":"한진그룹 계열의 국내 최대 항공운송회사. 항공기 리스계약이 외화로 이루어지기 때문에 환율이 하락하면 원화로 환산한 차입금이 줄어 부채비율이 개선되는 효과 발생.","007310":"식품 전문업체로 마요네즈, 케찹, 카레, 식초, 3분류, 라면, 참기름, 참치 등 생산. 원재료(팜유 등) 수입 비중이 높아 환율하락시 수혜주로 부각됨.","004020":"현대자동차계열로 H형강, 철근 부문에서 국내 최대의 전기로 제강업체. 원재료(철광석, 석탄 등) 수입 비중이 높아 환율하락시 수혜주로 부각됨.","103140":"비철금속의 소재(동 및 동합금 판/대, 관, 봉/선, 소전 등)를 제조, 판매하는 신동사업을 영위. 원재료(전기동, 아연, 니켈 등) 수입 비중이 높아 환율하락시 수혜주로 부각됨.","097950":"국내 최대 종합식품업체로 원재료(원당, 원맥, 대두) 수입 비중이 높아 환율하락시 수혜주로 부각.","039130":"여행주는 환율하락시 내국인의 해외여행 비용 부담이 줄어 여행객 수가 증가하는 특성이 있기 때문에 대표적인 환율하락 수혜주로 분류됨.","015760":"국내 발전 및 송전사업을 책임지고 있는 공기업으로 전기판매, 원자력발전, 화력발전, 기타(발전소 설계 및 정비 등)사업을 영위. 유연탄, LNG 등의 연료가 대부분 환율 변동에 노출되어 있어 환율하락시 수혜주로 분류됨.","036460":"천연가스 도입 및 도매시장에서 독점적 지위를 보유한 정부출자 공기업. 해외의 천연가스 생산지로부터 LNG를 도입하여 국내의 발전사 및 도시가스사에게 전국배관망과 탱크로리 등을 통해 공급. 천연가스 도입단가는 국제유가와 환율에 따라 변동되는 특성이 있어 환율하락시 비용절감 효과로 수혜주로 부각됨.","010130":"세계적인 비철금속 제련업체로 아연과 연의 생산판매를 주력으로 하며, 금, 은, 황산등은 아연과 연 제련과정에서 회수하는 유가금속과 부산물의 일종으로 생산. 원재료(아연정광, 연정광 등) 수입 비중이 높아 환율하락시 수혜주로 부각.","001680":"종합식품사업 및 소재사업을 영위하는 식품 전문 업체. 원재료(옥수수, 원당, 당밀 등) 수입 비중이 높아 환율하락시 수혜주로 부각.","000070":"삼양그룹 계열의 지주회사로 지주사업과 투자 및 임대사업을 영위. 삼양사(식품, 화학 등 영위), 삼양패키징, 삼양바이오팜 등의 자회사를 보유. 자회사들의 원재료(원당, 옥수수 등) 수입 비중이 높아 환율하락시 수혜주로 부각됨.","004370":"국내 최대의 라면 생산업체. 라면(신라면, 너구리, 안성탕면 등), 스낵(새우깡 등) 등의 사업 영위. 원재료(소맥, 팜유 등) 수입비중이 높아 환율하락시 수혜주로 부각.","020560":"금호아시아나 그룹 계열의 국내 메이저 항공운송회사. 항공기 리스계약이 외화로 이뤄져 환율 하락시 원화 환산한 차입금이 줄어 부채비율 개선 효과가 발생.","005880":"철광석, 석탄, 천연가스 원유 등의 에너지 및 자원을 전문적으로 수송하는 대표적인 벌크선사로 LNG선, 탱커선, 컨테이너선 등의 해운업 영위업체. 환율하락시 선박유 비용절감 효과로 수혜주로 부각됨."}},"resultCode":"success"}