{"result":{"totCnt":7,"itemList":[{"cd":"001250","nm":"GS글로벌","mt":"0","nv":1820,"cv":90,"cr":5.2,"rf":"2","pcv":1730,"mks":1502,"aq":1894088,"aa":3437,"ms":"OPEN"},{"cd":"028260","nm":"삼성물산","mt":"0","nv":114500,"cv":4000,"cr":3.62,"rf":"2","pcv":110500,"mks":213986,"aq":1012137,"aa":116393,"ms":"OPEN"},{"cd":"001120","nm":"LG상사","mt":"0","nv":15950,"cv":450,"cr":2.9,"rf":"2","pcv":15500,"mks":6182,"aq":349593,"aa":5433,"ms":"OPEN"},{"cd":"047050","nm":"포스코인터내셔널","mt":"0","nv":14450,"cv":250,"cr":1.76,"rf":"2","pcv":14200,"mks":17828,"aq":231004,"aa":3283,"ms":"OPEN"},{"cd":"001740","nm":"SK네트웍스","mt":"0","nv":5360,"cv":80,"cr":1.52,"rf":"2","pcv":5280,"mks":13303,"aq":767232,"aa":4085,"ms":"OPEN"},{"cd":"011760","nm":"현대상사","mt":"0","nv":14650,"cv":200,"cr":1.38,"rf":"2","pcv":14450,"mks":1938,"aq":68704,"aa":1001,"ms":"OPEN"},{"cd":"298020","nm":"효성티앤씨","mt":"0","nv":113500,"cv":-500,"cr":-0.44,"rf":"5","pcv":114000,"mks":4912,"aq":20729,"aa":2335,"ms":"OPEN"}],"itemInfoMap":{"298020":"(주)효성에서 섬유 및 무역사업이 인적분할되어 재상장된 업체. 철강 및 화학제품 판매 등의 무역사업 영위.","011760":"국내 대표적인 종합상사. 사업부문은 산업플랜트(선박 및 엔진 등 관련 기자재, 플랜트, 전기/기계류, 그린에너지, 건설장비 등), 차량소재(자동차 및 부품, 철도차량 및 철도시스템, 석유 등), 철강(강판, 강관, 형강 제품 및 스테인레스 제품 등), 자원개발 등으로 구성.","028260":"삼성그룹 계열의 업계 선두권 종합상사. 자원개발, 철강, 화학, 전자재료, 섬유 등 다양한 방면에서 국제무역을 진행.","001740":"SK그룹 계열의 종합상사. 사업부문은 정보통신(이동통신 관련 유통 사업 등), Mobility(차량 정비부품 등), 상사(철강, 에너지, 화학 상품의 국내외 무역 및 석탄 자원개발 등), SK매직(가스기기, 전기, 전자기기), 워커힐(Grand Walkerhill Seoul 호텔(舊 쉐라톤 호텔), Vista Walkerhill Seoul 호텔(舊 W호텔), 인천공항 환승호텔 등) 등으로 구분.","047050":"POSCO그룹 계열의 종합상사. 미국, 중국, 일본, 독일, 인도네시아 등에 해외 법인을 두고 무역, 생산, 판매, 유통, 자원개발분야 등의 사업을 영위.","001250":"그룹 계열의 종합 무역상사. 철강금속과 자원물자(석유/화학제품, 시멘트, 기계플랜트, 석탄 등) 등 산업용 소재 수출입과 삼국간 거래 등을 주요 사업으로 영위.","001120":"LG그룹 계열의 종합무역상사. 에너지/팜 부문(석탄, 팜 등), 산업재/솔루션 부문(화학, 프로젝트, 전기/전자 부품 등), 물류 부문(복합운송주선, 창고보관업 등) 등을 영위."}},"resultCode":"success"}