{"result":{"totCnt":9,"itemList":[{"cd":"066570","nm":"LG전자","mt":"0","nv":87900,"cv":4900,"cr":5.9,"rf":"2","pcv":83000,"mks":143846,"aq":1646140,"aa":138763,"ms":"OPEN"},{"cd":"037070","nm":"파세코","mt":"1","nv":14200,"cv":400,"cr":2.9,"rf":"2","pcv":13800,"mks":1988,"aq":240497,"aa":3375763,"ms":"OPEN"},{"cd":"002700","nm":"신일전자","mt":"0","nv":1905,"cv":45,"cr":2.42,"rf":"2","pcv":1860,"mks":1353,"aq":1781554,"aa":3375,"ms":"OPEN"},{"cd":"284740","nm":"쿠쿠홈시스","mt":"0","nv":40800,"cv":250,"cr":0.62,"rf":"2","pcv":40550,"mks":9154,"aq":41042,"aa":1658,"ms":"OPEN"},{"cd":"005930","nm":"삼성전자","mt":"0","nv":58500,"cv":300,"cr":0.52,"rf":"2","pcv":58200,"mks":3492323,"aq":12451136,"aa":724673,"ms":"OPEN"},{"cd":"071460","nm":"위니아딤채","mt":"1","nv":2410,"cv":-15,"cr":-0.62,"rf":"5","pcv":2425,"mks":867,"aq":57023,"aa":136926,"ms":"OPEN"},{"cd":"021240","nm":"코웨이","mt":"0","nv":85900,"cv":-2100,"cr":-2.39,"rf":"5","pcv":88000,"mks":63394,"aq":132908,"aa":11378,"ms":"OPEN"},{"cd":"058610","nm":"에스피지","mt":"1","nv":6710,"cv":-190,"cr":-2.75,"rf":"5","pcv":6900,"mks":1401,"aq":114905,"aa":772918,"ms":"OPEN"},{"cd":"044340","nm":"위닉스","mt":"1","nv":20550,"cv":-600,"cr":-2.84,"rf":"5","pcv":21150,"mks":3673,"aq":222861,"aa":4601406,"ms":"OPEN"}],"itemInfoMap":{"002700":"선풍기, 제습기, 난로, 밥통/밥솥, 환풍기, 청소기 등을 생산, 판매하는 소형가전 전문 제조업체.","071460":"대유위니아그룹 계열의 종합가전 업체. 프리미엄 냉장고 및 압력밥솥, 공기청정기, 제습기 사업도 영위. 제습기 WDHG16D3HD, EDHA11W3 등을 생산중.","044340":"\"위닉스 뽀송\"이라는 브랜드의 제습기를 출시했으며, 가정용/산업용 제습기를 판매.","066570":"다양한 제습기 모델을 출시하여 판매.","037070":"제습기(PHD-F150HD)등을 출시하여 판매. 제습기 자체 생산시설을 보유.","005930":"CE 사업부문(TV, 모니터, 냉장고, 세탁기, 에어컨 등)에서 다양한 모델의 제습기를 생산/판매.","284740":"기존 쿠쿠전자에서 렌탈사업부문이 분할되어 재상장된 업체. 공기청정기, 정수기, 비데 등 생활가전 렌탈사업을 주요 사업으로 영위. 공기청정제습기(AC-24W20FW, AC-12Y10FW(I) 등)를 출시.","021240":"제습공기청정기(APD-1015B, APT-1014E 등) 제품군을 출시하여 판매.","058610":"정밀 제어용 기어드 모터 생산업체로 공기청정기와 제습기에 쓰이는 가정용 Fan BLDC 모터를 생산중."}},"resultCode":"success"}