{"result":{"totCnt":28,"itemList":[{"cd":"286940","nm":"롯데정보통신","mt":"0","nv":35450,"cv":750,"cr":2.16,"rf":"2","pcv":34700,"mks":5458,"aq":55054,"aa":1927,"ms":"OPEN"},{"cd":"042510","nm":"라온시큐어","mt":"1","nv":3845,"cv":80,"cr":2.12,"rf":"2","pcv":3765,"mks":1223,"aq":2270315,"aa":8831588,"ms":"OPEN"},{"cd":"018260","nm":"삼성에스디에스","mt":"0","nv":168500,"cv":3000,"cr":1.81,"rf":"2","pcv":165500,"mks":130382,"aq":161820,"aa":27149,"ms":"OPEN"},{"cd":"047080","nm":"한빛소프트","mt":"1","nv":3790,"cv":65,"cr":1.74,"rf":"2","pcv":3725,"mks":939,"aq":1095113,"aa":4109763,"ms":"OPEN"},{"cd":"085910","nm":"네오티스","mt":"1","nv":3950,"cv":40,"cr":1.02,"rf":"2","pcv":3910,"mks":435,"aq":19262,"aa":75613,"ms":"OPEN"},{"cd":"003550","nm":"LG","mt":"0","nv":88100,"cv":800,"cr":0.92,"rf":"2","pcv":87300,"mks":152023,"aq":384872,"aa":33042,"ms":"OPEN"},{"cd":"030200","nm":"KT","mt":"0","nv":24950,"cv":200,"cr":0.81,"rf":"2","pcv":24750,"mks":65147,"aq":1491429,"aa":36998,"ms":"OPEN"},{"cd":"017670","nm":"SK텔레콤","mt":"0","nv":238000,"cv":1000,"cr":0.42,"rf":"2","pcv":237000,"mks":192175,"aq":310389,"aa":73391,"ms":"OPEN"},{"cd":"034730","nm":"SK","mt":"0","nv":241000,"cv":500,"cr":0.21,"rf":"2","pcv":240500,"mks":169568,"aq":188511,"aa":45009,"ms":"OPEN"},{"cd":"035720","nm":"카카오","mt":"0","nv":353000,"cv":500,"cr":0.14,"rf":"2","pcv":352500,"mks":310689,"aq":470810,"aa":164802,"ms":"OPEN"},{"cd":"038160","nm":"팍스넷","mt":"1","nv":862,"cv":0,"cr":0.0,"rf":"3","pcv":862,"mks":106,"aq":0,"aa":0,"ms":"OPEN"},{"cd":"141020","nm":"포티스","mt":"1","nv":108,"cv":0,"cr":0.0,"rf":"3","pcv":108,"mks":188,"aq":0,"aa":0,"ms":"OPEN"},{"cd":"950110","nm":"SBI핀테크솔루션즈","mt":"1","nv":6990,"cv":-50,"cr":-0.71,"rf":"5","pcv":7040,"mks":1681,"aq":19479,"aa":136557,"ms":"OPEN"},{"cd":"041460","nm":"한국전자인증","mt":"1","nv":5980,"cv":-50,"cr":-0.83,"rf":"5","pcv":6030,"mks":1283,"aq":286012,"aa":1724723,"ms":"OPEN"},{"cd":"184230","nm":"SGA솔루션즈","mt":"1","nv":801,"cv":-8,"cr":-0.99,"rf":"5","pcv":809,"mks":294,"aq":121653,"aa":97397,"ms":"OPEN"},{"cd":"068940","nm":"아이씨케이","mt":"1","nv":4650,"cv":-50,"cr":-1.06,"rf":"5","pcv":4700,"mks":1450,"aq":155679,"aa":716933,"ms":"OPEN"},{"cd":"203650","nm":"드림시큐리티","mt":"1","nv":3765,"cv":-55,"cr":-1.44,"rf":"5","pcv":3820,"mks":1905,"aq":1687262,"aa":6380298,"ms":"OPEN"},{"cd":"054920","nm":"한컴위드","mt":"1","nv":3770,"cv":-60,"cr":-1.57,"rf":"5","pcv":3830,"mks":1064,"aq":408488,"aa":1518634,"ms":"OPEN"},{"cd":"150900","nm":"파수","mt":"1","nv":5070,"cv":-90,"cr":-1.74,"rf":"5","pcv":5160,"mks":512,"aq":63894,"aa":328258,"ms":"OPEN"},{"cd":"139050","nm":"데일리블록체인","mt":"1","nv":532,"cv":-10,"cr":-1.85,"rf":"5","pcv":542,"mks":285,"aq":291561,"aa":155468,"ms":"OPEN"}],"itemInfoMap":{"018260":"2016년 글로벌 블록체인 오픈소스 개발 컨소시엄에 참여하는 등 블록체인을 접목한 신규 사업 추진 강화중. 기업용 블록체인 플랫폼 '넥스레저' 및 블록체인 신분증 등을 비롯해 은행 공동 블록체인 인증 시스템인 뱅크사인(BankSign)을 개발.","027830":"삼성SDS와 공동으로 블록체인 업체인 블로코에 투자를 단행한 것으로 알려지면서 시장에서 부각.","286940":"롯데그룹 계열의 SM(System Management) 및 SI(System Integration) 전문 업체. AI, 빅데이터, 블록체인, IoT, 클라우드 컴퓨팅 등 4차 산업혁명, 디지털 트랜스포메이션 관련분야 신사업 추진중. 블록체인 담당을 별도로 신설하여 개발된 솔루션의 블록체인을 통한 암호화 기술 연구.","030200":"블록체인 기술을 활용한 전자서명 이미지(Electronic data & Signature Capture)관리 시스템을 개발. 18년 조직개편을 통해 5G와 블록체인 전담조직을 신설.","184230":"국내 최초 비트코인 보안 기술 개발 업체로 블록체인 인증 및 위변조 방지 기술 보유. 삼성SDS를 통해 은행연합회가 추진 중인 ‘은행 공동 블록체인 인증 시스템 구축 사업’에 참여. 암호 기반 인증 및 전자사업 사업 등을 영위하는 블록체인 전문기업 SGA비엘씨(주)를 종속회사로 보유.","047080":"18년4월 동사의 글로벌 게임 자산 거래 블록체인 플랫폼 ‘브릴라이트(Bryllite)’ ICO 홈페이지를 정식 오픈했으며, 18년10월 글로벌 암호화폐거래소 비트포렉스에 상장.","017670":"18년1월 신사업부로 블록체인사업개발유닛(블록체인유닛)을 신규 설립.","039420":"17년5월에 발족한 삼성SDS 해운물류 블록체인 컨소시엄에 참여.","141020":"17년7월 블록체인 기술전문 업체인 코인플러그와 동남아시아지역에 블록체인 기반 오픈페이먼트 솔루션 적용을 위한 공동 사업협약 체결했으며, 블록체인 등 플랫폼 사업 강화를 추진중.","139050":"옐로모바일이 블록체인 사업 강화를 위해 동사를 인수. 18년5월 블록체인 기술 기업 및 ICO 추진 글로벌 기업 투자를 목적으로 (주)데일리크립토IB를 설립.","003550":"자회사인 LG CNS가 금융 블록체인 컨소시엄인 R3와 사업 협약을 체결하여 LG CNS 블록체인 플랫폼을 출시.","192250":"매쉬형 블록체인 기반 기술 개발. 17년 이더리움 블록체인 기반의 기기간 상호인증 기술 개발을 완료. 암호화폐 전자지갑 '터치엑스월렛(TouchxWallet)'을 개발.","131090":"Secure OS 및 커널레벨 암호화 기술을 토대로 독창적인 블록체인 보안 기술 개발.","085910":"2018년1월 계열사인 유니포인트가 한국예탁결제원 전자투표업무에 블록체인 기술 적용을 위한 개념검증(PoC) 사업을 완료. 유니포인트는 블록체인 오픈소스 '하이퍼레저 패브릭(Hyperledger Fabric)'을 이용하여 업무 시스템 구축, 서비스 및 컨설팅을 제공하는 사업을 영위.","054920":"17년10월 현대페이와 블록체인 기반 플랫폼 및 서비스 개발을 위한 업무협약 체결. 18년3월 기존에 보유한 통합 키(Key) 관리, 공개키기반구조(PKI), 파이도(FIDO) 생체인증, 통합인증 등의 보안 솔루션에 블록체인 기술을 적용해 보안성을 강화한 '블록체인 시큐리티 스위트(Blockchain Security Suite)' 출시.","000700":"자회사 싸이버로지텍이 삼성SDS와 총 38개 민관연으로 결성된 해운물류 블록체인 컨소시엄에 참여.","044380":"블록체인을 기반으로 복잡한 연산 처리가 가능한 신제품 '크립토(Crypto) PC'와 가정에서 블록체인 암호화 해독 체험을 해볼 수 있는 '홈 크립토(Home Crypto) PC'를 출시.","038160":"블록체인 신사업 추진을 위해 18년7월 자회사 (주)비트팍스를 설립. 블록체인 기반 탈중앙화 방식 메신저 '쉬(Shh)' 서비스 개발.","053350":"KT와 블록체인 기반의 통합인증, 권한관리 솔루션 공동개발.","034730":"자회사인 SK C&C가 기업 범용 블록체인 디지털 서비스 및 국내 선사 대상 블록체인 기반 물류 서비스 개발.","035420":"18년4월 자회사 라인의 국내 법인인 라인플러스가 블록체인 기술 전문 자회사 '언블락'을 출범.","203650":"삼성SDS와 전국은행연합회에서 추진 중인 18개 은행 공동 ‘블록체인 인증시스템 구축 사업’에 공동 참여.","150900":"블록체인 기반의 진본 증명 플랫폼인 '파수블록(Fasoo Block)'을 개발하여 제공 중.","035720":"18년3월 블록체인 기술 및 서비스 자회사 '그라운드X' 설립했으며, 19년6월 그라운드X가 블록체인 플랫폼 '클레이튼'의 메인넷을 정식 출시.","068940":"자사 보유 블록체인 기술을 활용하여 금융 거래에 대한 중개 시스템인 TSM(Trusted Service Management)시스템 구축 계획.","950110":"리플 네트워크(Ripple Network)를 활용하여 블록체인 기반의 일본-태국간 국제 송금 서비스를 개시. 국내에서도 블록체인을 활용한 국제 송금 서비스 제공.","042510":"모바일, 유비쿼터스 및 기기인증 보안 솔루션을 보유한 전문 보안 솔루션 개발 업체. 18년2월 블록체인 전문기업 더루프와 블록체인 기반 생체인증(FIDO) 시스템 공동개발을 위한 업무협약 체결.","041460":"서울대학교 분산 컴퓨팅랩과 함께 블록체인 연구개발(R&D) 사업자로 선정."}},"resultCode":"success"}